[
    {
        "name": "北宫结",
        "infobox": [
            [
                "国家",
                "卫"
            ],
            [
                "名",
                "结"
            ],
            [
                "氏",
                "北宫"
            ],
            [
                "姓",
                "姬"
            ],
            [
                "时代",
                "春秋"
            ],
            [
                "谥号",
                "贞"
            ]
        ]
    },
    {
        "name": "北宫括",
        "infobox": [
            [
                "子女",
                "北宫佗"
            ],
            [
                "国家",
                "卫"
            ],
            [
                "名",
                "括"
            ],
            [
                "氏",
                "北宫"
            ],
            [
                "姓",
                "姬"
            ],
            [
                "时代",
                "春秋"
            ],
            [
                "谥号",
                "懿"
            ]
        ]
    },
    {
        "name": "北宫佗",
        "infobox": [
            [
                "子女",
                "北宫喜"
            ],
            [
                "国家",
                "卫"
            ],
            [
                "名",
                "佗"
            ],
            [
                "氏",
                "北宫"
            ],
            [
                "姓",
                "姬"
            ],
            [
                "时代",
                "春秋"
            ],
            [
                "父",
                "北宫括"
            ],
            [
                "谥号",
                "文"
            ]
        ]
    },
    {
        "name": "北宫喜",
        "infobox": [
            [
                "国家",
                "卫"
            ],
            [
                "名",
                "喜"
            ],
            [
                "氏",
                "北宫"
            ],
            [
                "姓",
                "姬"
            ],
            [
                "时代",
                "春秋"
            ],
            [
                "父",
                "北宫文子"
            ],
            [
                "谥号",
                "贞"
            ]
        ]
    },
    {
        "name": "荀林父",
        "infobox": [
            [
                "子女",
                "荀庚"
            ],
            [
                "时代",
                "春秋时期"
            ],
            [
                "名",
                "林父"
            ],
            [
                "氏",
                "荀、中行"
            ],
            [
                "父",
                "逝敖"
            ],
            [
                "谥号",
                "桓"
            ],
            [
                "身份",
                "晋国上军将 晋国中军佐"
            ]
        ]
    },
    {
        "name": "公子喜",
        "infobox": [
            [
                "子女",
                "公孙舍之（子展），公孙鉏"
            ],
            [
                "国家",
                "郑国"
            ],
            [
                "官位",
                "郑卿（当国）"
            ],
            [
                "名",
                "喜"
            ],
            [
                "姓",
                "姬"
            ],
            [
                "字",
                "子罕"
            ],
            [
                "父",
                "郑穆公"
            ]
        ]
    },
    {
        "name": "公子贞",
        "infobox": [
            [
                "子女",
                "郄尹"
            ],
            [
                "时代",
                "春秋时期"
            ],
            [
                "名",
                "贞"
            ],
            [
                "姓",
                "芈"
            ],
            [
                "字",
                "子囊"
            ],
            [
                "父",
                "楚庄王"
            ],
            [
                "身份",
                "楚国令尹"
            ]
        ]
    },
    {
        "name": "管仲",
        "infobox": [
            [
                "逝世",
                "前645年 齐国"
            ],
            [
                "出生",
                "前725年 颍上"
            ],
            [
                "元配",
                "不详"
            ],
            [
                "名",
                "夷吾"
            ],
            [
                "父亲",
                "管严"
            ],
            [
                "氏",
                "管"
            ],
            [
                "子",
                "管伍"
            ],
            [
                "姓",
                "姬"
            ],
            [
                "侧室",
                "婧（姓氏不详）"
            ],
            [
                "字",
                "仲"
            ],
            [
                "谥号",
                "敬"
            ]
        ]
    },
    {
        "name": "虢公丑",
        "infobox": [
            [
                "国家",
                "南、北虢国"
            ],
            [
                "在位年代",
                "？—前655年"
            ],
            [
                "名",
                "丑"
            ],
            [
                "氏",
                "虢叔"
            ],
            [
                "姓",
                "姬"
            ],
            [
                "别称",
                "虢公"
            ],
            [
                "时代",
                "春秋"
            ],
            [
                "都城",
                "上阳"
            ],
            [
                "身份",
                "南、北虢国君主"
            ]
        ]
    },
    {
        "name": "韩厥",
        "infobox": [
            [
                "子女",
                "韩无忌、韩起"
            ],
            [
                "国家",
                "晋国"
            ],
            [
                "官位",
                "晋国中军将"
            ],
            [
                "名",
                "厥"
            ],
            [
                "氏",
                "韩"
            ],
            [
                "姓",
                "姬"
            ],
            [
                "时代",
                "春秋"
            ],
            [
                "别名",
                "韩献子"
            ],
            [
                "父",
                "韩子舆"
            ],
            [
                "谥号",
                "献"
            ],
            [
                "身份",
                "卿"
            ]
        ]
    },
    {
        "name": "狐偃",
        "infobox": [
            [
                "子女",
                "狐射姑"
            ],
            [
                "国家",
                "晋国"
            ],
            [
                "官位",
                "晋国上军将"
            ],
            [
                "名",
                "偃"
            ],
            [
                "别名",
                "咎犯、舅犯"
            ],
            [
                "姓",
                "姬"
            ],
            [
                "时代",
                "春秋"
            ],
            [
                "氏",
                "狐"
            ],
            [
                "字",
                "子犯"
            ],
            [
                "父",
                "狐突"
            ],
            [
                "身份",
                "卿"
            ]
        ]
    },
    {
        "name": "华元",
        "infobox": [
            [
                "子女",
                "华阅、华臣"
            ],
            [
                "国家",
                "宋国"
            ],
            [
                "名",
                "元"
            ],
            [
                "太子",
                "华阅"
            ],
            [
                "氏",
                "华"
            ],
            [
                "姓",
                "子"
            ],
            [
                "时代",
                "春秋时期"
            ],
            [
                "父",
                "华御事"
            ],
            [
                "身份",
                "宋国右师"
            ]
        ]
    },
    {
        "name": "季平子",
        "infobox": [
            [
                "子女",
                "季桓子季孙斯"
            ],
            [
                "国家",
                "鲁国"
            ],
            [
                "逝世日期",
                "前505年"
            ],
            [
                "名",
                "意如"
            ],
            [
                "氏",
                "季孙"
            ],
            [
                "姓",
                "姬"
            ],
            [
                "时代",
                "春秋"
            ],
            [
                "别名",
                "季平子"
            ],
            [
                "父",
                "季悼子季孙纥"
            ],
            [
                "谥号",
                "平"
            ],
            [
                "身份",
                "鲁国正卿"
            ]
        ]
    },
    {
        "name": "季文子",
        "infobox": [
            [
                "子女",
                "季武子季孙宿"
            ],
            [
                "国家",
                "鲁国"
            ],
            [
                "逝世日期",
                "前568年"
            ],
            [
                "名",
                "行父"
            ],
            [
                "氏",
                "季孙"
            ],
            [
                "姓",
                "姬"
            ],
            [
                "时代",
                "春秋"
            ],
            [
                "别名",
                "季文子"
            ],
            [
                "父",
                "齐仲无佚"
            ],
            [
                "谥号",
                "文"
            ],
            [
                "身份",
                "鲁国正卿"
            ]
        ]
    },
    {
        "name": "季武子",
        "infobox": [
            [
                "子女",
                "季悼子季孙纥"
            ],
            [
                "国家",
                "鲁国"
            ],
            [
                "逝世日期",
                "前535年"
            ],
            [
                "名",
                "宿"
            ],
            [
                "氏",
                "季孙"
            ],
            [
                "姓",
                "姬"
            ],
            [
                "时代",
                "春秋"
            ],
            [
                "别名",
                "季武子、季孙夙"
            ],
            [
                "父",
                "季文子季孙行父"
            ],
            [
                "谥号",
                "武"
            ],
            [
                "身份",
                "鲁国正卿"
            ]
        ]
    },
    {
        "name": "季文子",
        "infobox": [
            [
                "子女",
                "季武子季孙宿"
            ],
            [
                "国家",
                "鲁国"
            ],
            [
                "逝世日期",
                "前568年"
            ],
            [
                "名",
                "行父"
            ],
            [
                "氏",
                "季孙"
            ],
            [
                "姓",
                "姬"
            ],
            [
                "时代",
                "春秋"
            ],
            [
                "别名",
                "季文子"
            ],
            [
                "父",
                "齐仲无佚"
            ],
            [
                "谥号",
                "文"
            ],
            [
                "身份",
                "鲁国正卿"
            ]
        ]
    },
    {
        "name": "季武子",
        "infobox": [
            [
                "子女",
                "季悼子季孙纥"
            ],
            [
                "国家",
                "鲁国"
            ],
            [
                "逝世日期",
                "前535年"
            ],
            [
                "名",
                "宿"
            ],
            [
                "氏",
                "季孙"
            ],
            [
                "姓",
                "姬"
            ],
            [
                "时代",
                "春秋"
            ],
            [
                "别名",
                "季武子、季孙夙"
            ],
            [
                "父",
                "季文子季孙行父"
            ],
            [
                "谥号",
                "武"
            ],
            [
                "身份",
                "鲁国正卿"
            ]
        ]
    },
    {
        "name": "季札",
        "infobox": [
            [
                "子女",
                "逞"
            ],
            [
                "姓",
                "姬"
            ],
            [
                "时代",
                "春秋时期"
            ],
            [
                "名",
                "札"
            ],
            [
                "父",
                "寿梦"
            ]
        ]
    },
    {
        "name": "季札",
        "infobox": [
            [
                "子女",
                "逞"
            ],
            [
                "姓",
                "姬"
            ],
            [
                "时代",
                "春秋时期"
            ],
            [
                "名",
                "札"
            ],
            [
                "父",
                "寿梦"
            ]
        ]
    },
    {
        "name": "简子",
        "infobox": [
            [
                "教育程度",
                "世新大学广电系电影组"
            ],
            [
                "本名",
                "简德瀚"
            ],
            [
                "英文名",
                "Hanson Chien"
            ],
            [
                "出生",
                "(1991-05-29) 1991年5月29日（26岁）"
            ],
            [
                "国籍",
                "台湾"
            ],
            [
                "职业",
                "魔术师、魔术顾问"
            ]
        ]
    },
    {
        "name": "晋悼公",
        "infobox": [
            [
                "逝世",
                "前558年"
            ],
            [
                "出生",
                "前586年"
            ],
            [
                "名",
                "周"
            ],
            [
                "父",
                "惠伯谈"
            ],
            [
                "太子",
                "太子彪"
            ],
            [
                "正妻",
                "晋悼夫人"
            ],
            [
                "姓",
                "姬"
            ],
            [
                "国家",
                "晋国"
            ],
            [
                "时代",
                "东周春秋时期"
            ],
            [
                "在位",
                "前573年二月-前558年十一月"
            ],
            [
                "谥号",
                "悼公"
            ]
        ]
    },
    {
        "name": "晋悼公",
        "infobox": [
            [
                "逝世",
                "前558年"
            ],
            [
                "出生",
                "前586年"
            ],
            [
                "名",
                "周"
            ],
            [
                "父",
                "惠伯谈"
            ],
            [
                "太子",
                "太子彪"
            ],
            [
                "正妻",
                "晋悼夫人"
            ],
            [
                "姓",
                "姬"
            ],
            [
                "国家",
                "晋国"
            ],
            [
                "时代",
                "东周春秋时期"
            ],
            [
                "在位",
                "前573年二月-前558年十一月"
            ],
            [
                "谥号",
                "悼公"
            ]
        ]
    },
    {
        "name": "晋景公",
        "infobox": [
            [
                "国家",
                "晋国"
            ],
            [
                "名",
                "獳、据"
            ],
            [
                "父",
                "晋成公"
            ],
            [
                "太子",
                "太子州蒲"
            ],
            [
                "姓",
                "姬"
            ],
            [
                "逝世",
                "前581年"
            ],
            [
                "时代",
                "春秋时期"
            ],
            [
                "在位",
                "前599年-前581年"
            ],
            [
                "谥号",
                "景"
            ]
        ]
    },
    {
        "name": "晋文公",
        "infobox": [
            [
                "在世",
                "前697年－前628年"
            ],
            [
                "父",
                "晋献公"
            ],
            [
                "母",
                "狐季姬"
            ],
            [
                "在位",
                "前636年夏历二月 - 前628年夏历9月9日(儒略历10月27日)"
            ],
            [
                "谥号",
                "文公"
            ],
            [
                "政权",
                "晋国"
            ]
        ]
    },
    {
        "name": "晋景公",
        "infobox": [
            [
                "国家",
                "晋国"
            ],
            [
                "名",
                "獳、据"
            ],
            [
                "父",
                "晋成公"
            ],
            [
                "太子",
                "太子州蒲"
            ],
            [
                "姓",
                "姬"
            ],
            [
                "逝世",
                "前581年"
            ],
            [
                "时代",
                "春秋时期"
            ],
            [
                "在位",
                "前599年-前581年"
            ],
            [
                "谥号",
                "景"
            ]
        ]
    },
    {
        "name": "晋文公",
        "infobox": [
            [
                "在世",
                "前697年－前628年"
            ],
            [
                "父",
                "晋献公"
            ],
            [
                "母",
                "狐季姬"
            ],
            [
                "在位",
                "前636年夏历二月 - 前628年夏历9月9日(儒略历10月27日)"
            ],
            [
                "谥号",
                "文公"
            ],
            [
                "政权",
                "晋国"
            ]
        ]
    },
    {
        "name": "郤克",
        "infobox": [
            [
                "子女",
                "郤锜"
            ],
            [
                "官位",
                "晋国中军将"
            ],
            [
                "逝世日期",
                "前587年"
            ],
            [
                "名",
                "克"
            ],
            [
                "氏",
                "郤"
            ],
            [
                "姓",
                "姬"
            ],
            [
                "别称",
                "郤献子"
            ],
            [
                "父",
                "郤缺"
            ],
            [
                "谥号",
                "献"
            ]
        ]
    },
    {
        "name": "乐祁",
        "infobox": [
            [
                "子女",
                "乐溷"
            ],
            [
                "时代",
                "春秋时期"
            ],
            [
                "名",
                "祁"
            ],
            [
                "氏",
                "乐"
            ],
            [
                "姓",
                "子"
            ],
            [
                "字",
                "子梁"
            ],
            [
                "父",
                "乐喜的儿子"
            ],
            [
                "身份",
                "宋国司城"
            ]
        ]
    },
    {
        "name": "乐喜",
        "infobox": [
            [
                "子女",
                "乐祁的父亲"
            ],
            [
                "时代",
                "春秋时期"
            ],
            [
                "名",
                "喜"
            ],
            [
                "氏",
                "乐"
            ],
            [
                "姓",
                "子"
            ],
            [
                "字",
                "子罕"
            ],
            [
                "父",
                "西乡士曹"
            ],
            [
                "身份",
                "宋国司城"
            ]
        ]
    },
    {
        "name": "鲁隐公",
        "infobox": [
            [
                "年号",
                "无"
            ],
            [
                "在世",
                "？ - 前712年"
            ],
            [
                "父",
                "鲁惠公"
            ],
            [
                "母",
                "声子"
            ],
            [
                "陵墓",
                "不详"
            ],
            [
                "姓名",
                "息姑"
            ],
            [
                "在位",
                "前722年正月 - 前712年鲁历11月15日"
            ],
            [
                "谥号",
                "隐公"
            ],
            [
                "政权",
                "鲁国"
            ]
        ]
    },
    {
        "name": "鲁庄公",
        "infobox": [
            [
                "年号",
                "无"
            ],
            [
                "在世",
                "前706年10月7日－前662年8月11日（阴历八月初五癸亥）"
            ],
            [
                "父",
                "鲁桓公"
            ],
            [
                "母",
                "文姜"
            ],
            [
                "陵墓",
                "不详"
            ],
            [
                "在位",
                "前693年正月－前662年8月11日"
            ],
            [
                "谥号",
                "庄公"
            ],
            [
                "政权",
                "鲁国"
            ]
        ]
    },
    {
        "name": "栾书",
        "infobox": [
            [
                "子女",
                "栾黡、栾针"
            ],
            [
                "国家",
                "晋国"
            ],
            [
                "官位",
                "晋国中军将"
            ],
            [
                "名",
                "书"
            ],
            [
                "别名",
                "栾武子"
            ],
            [
                "姓",
                "姬"
            ],
            [
                "时代",
                "春秋"
            ],
            [
                "氏",
                "栾"
            ],
            [
                "父",
                "栾盾"
            ],
            [
                "谥号",
                "武"
            ],
            [
                "身份",
                "卿"
            ]
        ]
    },
    {
        "name": "栾书",
        "infobox": [
            [
                "子女",
                "栾黡、栾针"
            ],
            [
                "国家",
                "晋国"
            ],
            [
                "官位",
                "晋国中军将"
            ],
            [
                "名",
                "书"
            ],
            [
                "别名",
                "栾武子"
            ],
            [
                "姓",
                "姬"
            ],
            [
                "时代",
                "春秋"
            ],
            [
                "氏",
                "栾"
            ],
            [
                "父",
                "栾盾"
            ],
            [
                "谥号",
                "武"
            ],
            [
                "身份",
                "卿"
            ]
        ]
    },
    {
        "name": "栾盈",
        "infobox": [
            [
                "国家",
                "晋国"
            ],
            [
                "官位",
                "晋国下军将"
            ],
            [
                "逝世日期",
                "前550年"
            ],
            [
                "名",
                "盈"
            ],
            [
                "氏",
                "栾"
            ],
            [
                "姓",
                "姬"
            ],
            [
                "时代",
                "春秋"
            ],
            [
                "别名",
                "栾怀子、栾逞"
            ],
            [
                "父",
                "栾黡"
            ],
            [
                "谥号",
                "怀"
            ],
            [
                "身份",
                "晋国卿"
            ]
        ]
    },
    {
        "name": "孟献子",
        "infobox": [
            [
                "子女",
                "孟庄子仲孙速、仲孙它、懿伯"
            ],
            [
                "国家",
                "鲁国"
            ],
            [
                "逝世日期",
                "前554年"
            ],
            [
                "名",
                "蔑"
            ],
            [
                "别名",
                "仲孙蔑、孟献子"
            ],
            [
                "姓",
                "姬"
            ],
            [
                "时代",
                "春秋"
            ],
            [
                "氏",
                "孟孙"
            ],
            [
                "父",
                "孟文伯仲孙谷"
            ],
            [
                "出生日期",
                "约前624年"
            ],
            [
                "谥号",
                "献"
            ],
            [
                "身份",
                "鲁国卿"
            ]
        ]
    },
    {
        "name": "囊瓦",
        "infobox": [
            [
                "时代",
                "春秋时期"
            ],
            [
                "名",
                "瓦"
            ],
            [
                "氏",
                "囊"
            ],
            [
                "姓",
                "芈"
            ],
            [
                "字",
                "子常"
            ],
            [
                "父",
                "郄尹"
            ],
            [
                "身份",
                "楚国令尹"
            ]
        ]
    },
    {
        "name": "秦穆公",
        "infobox": [
            [
                "子女",
                "秦康公"
            ],
            [
                "国家",
                "秦国"
            ],
            [
                "名",
                "任好"
            ],
            [
                "父",
                "秦德公"
            ],
            [
                "太子",
                "秦康公"
            ],
            [
                "姓",
                "嬴"
            ],
            [
                "别称",
                "秦缪公"
            ],
            [
                "时代",
                "春秋"
            ],
            [
                "墓葬",
                "雍"
            ],
            [
                "谥号",
                "穆公"
            ],
            [
                "都城",
                "雍城"
            ]
        ]
    },
    {
        "name": "庆封",
        "infobox": [
            [
                "国家",
                "齐国"
            ],
            [
                "官位",
                "齐国大夫"
            ],
            [
                "逝世日期",
                "前538年"
            ],
            [
                "名",
                "封"
            ],
            [
                "太子",
                "庆舍"
            ],
            [
                "氏",
                "庆氏"
            ],
            [
                "姓",
                "姜"
            ],
            [
                "父",
                "庆克"
            ]
        ]
    },
    {
        "name": "屈建",
        "infobox": [
            [
                "子女",
                "屈生"
            ],
            [
                "时代",
                "春秋时期"
            ],
            [
                "名",
                "建"
            ],
            [
                "氏",
                "屈"
            ],
            [
                "姓",
                "芈"
            ],
            [
                "字",
                "子木"
            ],
            [
                "父",
                "屈到"
            ],
            [
                "身份",
                "楚国莫敖、令尹"
            ]
        ]
    },
    {
        "name": "屈瑕",
        "infobox": [
            [
                "国家",
                "楚国"
            ],
            [
                "官位",
                "莫敖"
            ],
            [
                "逝世日期",
                "前699年春季"
            ],
            [
                "名",
                "瑕"
            ],
            [
                "氏",
                "屈氏"
            ],
            [
                "姓",
                "芈"
            ],
            [
                "时代",
                "春秋"
            ],
            [
                "父",
                "楚武王"
            ],
            [
                "出生日期",
                "不详"
            ],
            [
                "身份",
                "楚国元帅"
            ]
        ]
    },
    {
        "name": "申叔时",
        "infobox": [
            [
                "国家",
                "楚国"
            ],
            [
                "名",
                "时"
            ],
            [
                "氏",
                "申叔"
            ],
            [
                "姓",
                "芈"
            ],
            [
                "时代",
                "春秋"
            ],
            [
                "身份",
                "楚国大夫"
            ]
        ]
    },
    {
        "name": "沈尹戌",
        "infobox": [
            [
                "子女",
                "叶公高"
            ],
            [
                "国家",
                "楚国"
            ],
            [
                "名",
                "戌"
            ],
            [
                "氏",
                "沈尹"
            ],
            [
                "姓",
                "芈"
            ],
            [
                "时代",
                "春秋时期"
            ],
            [
                "身份",
                "左司马"
            ]
        ]
    },
    {
        "name": "士会",
        "infobox": [
            [
                "子女",
                "士燮、士鲂"
            ],
            [
                "时代",
                "春秋时期"
            ],
            [
                "名",
                "会"
            ],
            [
                "氏",
                "士、范"
            ],
            [
                "姓",
                "祁"
            ],
            [
                "父",
                "成伯缺"
            ],
            [
                "谥号",
                "武"
            ],
            [
                "身份",
                "晋国代理车右 晋国上军将 晋国中军佐 晋国中军将、太傅"
            ]
        ]
    },
    {
        "name": "士景伯",
        "infobox": [
            [
                "国家",
                "晋"
            ],
            [
                "名",
                "弥牟"
            ],
            [
                "氏",
                "士"
            ],
            [
                "姓",
                "祁"
            ],
            [
                "时代",
                "春秋"
            ],
            [
                "父",
                "士文伯"
            ],
            [
                "谥号",
                "文"
            ]
        ]
    },
    {
        "name": "士蒍",
        "infobox": [
            [
                "子女",
                "士成伯士缺、士縠"
            ],
            [
                "国家",
                "晋国"
            ],
            [
                "官位",
                "大司空"
            ],
            [
                "名",
                "蔿"
            ],
            [
                "氏",
                "士"
            ],
            [
                "姓",
                "祁"
            ],
            [
                "时代",
                "春秋"
            ],
            [
                "字",
                "子与"
            ],
            [
                "父",
                "隰叔"
            ],
            [
                "身份",
                "晋国士师"
            ]
        ]
    },
    {
        "name": "士文伯",
        "infobox": [
            [
                "子女",
                "士景伯"
            ],
            [
                "国家",
                "晋"
            ],
            [
                "名",
                "匄"
            ],
            [
                "氏",
                "士"
            ],
            [
                "姓",
                "祁"
            ],
            [
                "时代",
                "春秋"
            ],
            [
                "字",
                "伯瑕"
            ],
            [
                "父",
                "士弱"
            ],
            [
                "谥号",
                "文"
            ]
        ]
    },
    {
        "name": "士鞅",
        "infobox": [
            [
                "子女",
                "范昭子 士吉射"
            ],
            [
                "国家",
                "鲁国"
            ],
            [
                "官位",
                "晋国下军佐 晋国中军佐 晋国中军将"
            ],
            [
                "名",
                "鞅"
            ],
            [
                "氏",
                "士、范"
            ],
            [
                "姓",
                "祁"
            ],
            [
                "别称",
                "范献子、范叔、范鞅"
            ],
            [
                "父",
                "范宣子 士匄"
            ],
            [
                "谥号",
                "献"
            ]
        ]
    },
    {
        "name": "士贞子",
        "infobox": [
            [
                "子女",
                "士庄伯"
            ],
            [
                "国家",
                "晋"
            ],
            [
                "名",
                "渥浊"
            ],
            [
                "氏",
                "士"
            ],
            [
                "姓",
                "祁"
            ],
            [
                "时代",
                "春秋"
            ],
            [
                "父",
                "士穆子"
            ],
            [
                "谥号",
                "贞"
            ]
        ]
    },
    {
        "name": "士庄伯",
        "infobox": [
            [
                "子女",
                "士文伯"
            ],
            [
                "国家",
                "晋"
            ],
            [
                "名",
                "弱"
            ],
            [
                "氏",
                "士"
            ],
            [
                "姓",
                "祁"
            ],
            [
                "时代",
                "春秋"
            ],
            [
                "父",
                "士贞子"
            ],
            [
                "谥号",
                "庄"
            ]
        ]
    },
    {
        "name": "叔带",
        "infobox": [
            [
                "国家",
                "晋国"
            ],
            [
                "时代",
                "西周"
            ],
            [
                "身份",
                "赵氏宗主"
            ],
            [
                "父",
                "奄父"
            ]
        ]
    },
    {
        "name": "叔弓",
        "infobox": [
            [
                "子女",
                "定伯阅、叔辄、叔鞅"
            ],
            [
                "时代",
                "春秋时期"
            ],
            [
                "名",
                "弓"
            ],
            [
                "氏",
                "子叔"
            ],
            [
                "姓",
                "姬"
            ],
            [
                "父",
                "叔老"
            ],
            [
                "谥号",
                "敬"
            ],
            [
                "身份",
                "鲁卿"
            ]
        ]
    },
    {
        "name": "叔虎",
        "infobox": [
            [
                "时代",
                "春秋时期"
            ],
            [
                "名",
                "虎"
            ],
            [
                "母",
                "羊舌姬"
            ],
            [
                "氏",
                "羊舌"
            ],
            [
                "姓",
                "姬"
            ],
            [
                "别字",
                "无"
            ],
            [
                "父",
                "羊舌职"
            ],
            [
                "身份",
                "晋国大夫"
            ]
        ]
    },
    {
        "name": "叔孙豹",
        "infobox": [
            [
                "子女",
                "竖牛、孟丙、仲壬、叔孙婼"
            ],
            [
                "国家",
                "鲁国"
            ],
            [
                "官位",
                "鲁国司马"
            ],
            [
                "名",
                "豹"
            ],
            [
                "别名",
                "穆叔、叔孙穆子"
            ],
            [
                "姓",
                "姬"
            ],
            [
                "时代",
                "春秋"
            ],
            [
                "氏",
                "叔孙"
            ],
            [
                "父",
                "叔孙庄叔"
            ],
            [
                "谥号",
                "穆"
            ],
            [
                "身份",
                "卿"
            ]
        ]
    },
    {
        "name": "叔孙婼",
        "infobox": [
            [
                "子女",
                "叔孙不敢"
            ],
            [
                "国家",
                "鲁国"
            ],
            [
                "官位",
                "鲁国司马"
            ],
            [
                "名",
                "婼"
            ],
            [
                "别名",
                "叔孙昭子"
            ],
            [
                "姓",
                "姬"
            ],
            [
                "时代",
                "春秋"
            ],
            [
                "氏",
                "叔孙"
            ],
            [
                "父",
                "叔孙豹"
            ],
            [
                "谥号",
                "昭"
            ],
            [
                "身份",
                "卿"
            ]
        ]
    },
    {
        "name": "叔孙豹",
        "infobox": [
            [
                "子女",
                "竖牛、孟丙、仲壬、叔孙婼"
            ],
            [
                "国家",
                "鲁国"
            ],
            [
                "官位",
                "鲁国司马"
            ],
            [
                "名",
                "豹"
            ],
            [
                "别名",
                "穆叔、叔孙穆子"
            ],
            [
                "姓",
                "姬"
            ],
            [
                "时代",
                "春秋"
            ],
            [
                "氏",
                "叔孙"
            ],
            [
                "父",
                "叔孙庄叔"
            ],
            [
                "谥号",
                "穆"
            ],
            [
                "身份",
                "卿"
            ]
        ]
    },
    {
        "name": "叔孙侨如",
        "infobox": [
            [
                "子女",
                "穆孟姬"
            ],
            [
                "国家",
                "鲁国"
            ],
            [
                "名",
                "侨如"
            ],
            [
                "氏",
                "叔孙"
            ],
            [
                "姓",
                "姬"
            ],
            [
                "时代",
                "春秋"
            ],
            [
                "父",
                "叔孙得臣"
            ],
            [
                "谥号",
                "宣"
            ],
            [
                "身份",
                "鲁国卿"
            ]
        ]
    },
    {
        "name": "叔孙婼",
        "infobox": [
            [
                "子女",
                "叔孙不敢"
            ],
            [
                "国家",
                "鲁国"
            ],
            [
                "官位",
                "鲁国司马"
            ],
            [
                "名",
                "婼"
            ],
            [
                "别名",
                "叔孙昭子"
            ],
            [
                "姓",
                "姬"
            ],
            [
                "时代",
                "春秋"
            ],
            [
                "氏",
                "叔孙"
            ],
            [
                "父",
                "叔孙豹"
            ],
            [
                "谥号",
                "昭"
            ],
            [
                "身份",
                "卿"
            ]
        ]
    },
    {
        "name": "叔肸",
        "infobox": [
            [
                "子女",
                "子叔声伯"
            ],
            [
                "国家",
                "鲁国"
            ],
            [
                "官位",
                "鲁卿"
            ],
            [
                "逝世日期",
                "前592年"
            ],
            [
                "名",
                "肸"
            ],
            [
                "姓",
                "姬"
            ],
            [
                "父",
                "鲁文公"
            ],
            [
                "谥号",
                "惠"
            ]
        ]
    },
    {
        "name": "叔向",
        "infobox": [
            [
                "子女",
                "羊舌食我"
            ],
            [
                "时代",
                "春秋时期"
            ],
            [
                "逝世日期",
                "约公元前528年或稍后"
            ],
            [
                "名",
                "肸"
            ],
            [
                "氏",
                "羊舌氏、杨氏"
            ],
            [
                "正妻",
                "夏姬之女"
            ],
            [
                "姓",
                "姬姓"
            ],
            [
                "国家",
                "晋国"
            ],
            [
                "别字",
                "叔誉"
            ],
            [
                "别名",
                "叔肸"
            ],
            [
                "字",
                "叔向"
            ],
            [
                "父",
                "羊舌职"
            ],
            [
                "身份",
                "大夫"
            ]
        ]
    },
    {
        "name": "宋文公",
        "infobox": [
            [
                "年号",
                "无"
            ],
            [
                "在世",
                "？－前589年"
            ],
            [
                "在位",
                "前610年－前589年"
            ],
            [
                "谥号",
                "文"
            ],
            [
                "政权",
                "宋国"
            ],
            [
                "庙号",
                "无"
            ]
        ]
    },
    {
        "name": "宋襄公",
        "infobox": [
            [
                "年号",
                "无"
            ],
            [
                "在世",
                "？－前637年"
            ],
            [
                "在位",
                "前650年－前637年"
            ],
            [
                "谥号",
                "襄"
            ],
            [
                "政权",
                "宋国"
            ],
            [
                "庙号",
                "无"
            ]
        ]
    },
    {
        "name": "宋元公",
        "infobox": [
            [
                "在世",
                "？—前517年"
            ],
            [
                "陵墓",
                "不明"
            ],
            [
                "姓名",
                "佐"
            ],
            [
                "在位",
                "前531年—前517年"
            ],
            [
                "谥号",
                "元"
            ],
            [
                "政权",
                "宋国"
            ]
        ]
    },
    {
        "name": "孙蒯",
        "infobox": [
            [
                "国家",
                "卫"
            ],
            [
                "名",
                "蒯"
            ],
            [
                "氏",
                "孙"
            ],
            [
                "姓",
                "姬"
            ],
            [
                "时代",
                "春秋时期"
            ],
            [
                "父",
                "孙林父"
            ]
        ]
    },
    {
        "name": "孙良夫",
        "infobox": [
            [
                "子女",
                "孙林父"
            ],
            [
                "国家",
                "卫"
            ],
            [
                "名",
                "良夫"
            ],
            [
                "氏",
                "孙"
            ],
            [
                "姓",
                "姬"
            ],
            [
                "时代",
                "春秋时期"
            ],
            [
                "父",
                "孙宣子"
            ],
            [
                "谥号",
                "桓"
            ]
        ]
    },
    {
        "name": "孙林父",
        "infobox": [
            [
                "子女",
                "孙嘉、孙襄、孙蒯"
            ],
            [
                "国家",
                "卫"
            ],
            [
                "名",
                "林父"
            ],
            [
                "氏",
                "孙"
            ],
            [
                "姓",
                "姬"
            ],
            [
                "时代",
                "春秋时期"
            ],
            [
                "父",
                "孙良夫"
            ],
            [
                "谥号",
                "文"
            ],
            [
                "身份",
                "上卿"
            ]
        ]
    },
    {
        "name": "孙叔敖",
        "infobox": [
            [
                "国家",
                "楚国"
            ],
            [
                "名",
                "敖"
            ],
            [
                "氏",
                "蔿"
            ],
            [
                "时代",
                "春秋"
            ],
            [
                "字",
                "孙叔"
            ],
            [
                "父",
                "蔿贾"
            ]
        ]
    },
    {
        "name": "孙周",
        "infobox": [
            [
                "语言",
                "汉语"
            ],
            [
                "籍贯",
                "山东掖县"
            ],
            [
                "出生",
                "(1954-08-01) 1954年8月1日（63岁） 中国"
            ],
            [
                "国籍",
                "中国"
            ],
            [
                "职业",
                "导演、摄影师、演员"
            ],
            [
                "民族",
                "汉族"
            ]
        ]
    },
    {
        "name": "蒍吕臣",
        "infobox": [
            [
                "子女",
                "蒍贾"
            ],
            [
                "国家",
                "楚"
            ],
            [
                "名",
                "吕臣"
            ],
            [
                "氏",
                "蒍"
            ],
            [
                "姓",
                "芈"
            ],
            [
                "时代",
                "春秋"
            ],
            [
                "父",
                "蒍章"
            ],
            [
                "身份",
                "楚国令尹"
            ]
        ]
    },
    {
        "name": "蒍子冯",
        "infobox": [
            [
                "子女",
                "蒍掩"
            ],
            [
                "时代",
                "春秋时期"
            ],
            [
                "名",
                "子冯"
            ],
            [
                "氏",
                "蒍"
            ],
            [
                "姓",
                "芈"
            ],
            [
                "身份",
                "楚国令尹"
            ]
        ]
    },
    {
        "name": "薳启彊",
        "infobox": [
            [
                "姓",
                "芈"
            ],
            [
                "时代",
                "春秋时期"
            ],
            [
                "名",
                "启彊"
            ],
            [
                "身份",
                "楚国太宰"
            ],
            [
                "氏",
                "薳"
            ]
        ]
    },
    {
        "name": "卫出公",
        "infobox": [
            [
                "政权",
                "卫国"
            ],
            [
                "谥号",
                "出"
            ],
            [
                "在位",
                "前493年—前481年/前477年—前470年（复位）"
            ],
            [
                "在世",
                "？—前456年"
            ],
            [
                "父",
                "卫后庄公"
            ]
        ]
    },
    {
        "name": "卫献公",
        "infobox": [
            [
                "政权",
                "卫国"
            ],
            [
                "谥号",
                "献"
            ],
            [
                "在位",
                "前576年—前559年/前546年—前544年（复位）"
            ],
            [
                "在世",
                "？—前544年"
            ],
            [
                "父",
                "卫定公"
            ]
        ]
    },
    {
        "name": "魏绛",
        "infobox": [
            [
                "子女",
                "魏舒"
            ],
            [
                "国家",
                "晋国"
            ],
            [
                "官位",
                "晋国上军佐"
            ],
            [
                "名",
                "绛"
            ],
            [
                "氏",
                "魏"
            ],
            [
                "姓",
                "姬"
            ],
            [
                "别称",
                "魏昭子、魏庄子"
            ],
            [
                "谥号",
                "昭、庄"
            ]
        ]
    },
    {
        "name": "魏舒",
        "infobox": [
            [
                "子女",
                "魏取"
            ],
            [
                "国家",
                "晋国"
            ],
            [
                "官位",
                "晋国中军将"
            ],
            [
                "名",
                "舒"
            ],
            [
                "氏",
                "魏"
            ],
            [
                "姓",
                "姬"
            ],
            [
                "时代",
                "春秋"
            ],
            [
                "别名",
                "魏献子、魏荼"
            ],
            [
                "父",
                "魏绛"
            ],
            [
                "谥号",
                "献"
            ],
            [
                "身份",
                "卿"
            ]
        ]
    },
    {
        "name": "赵武",
        "infobox": [
            [
                "子女",
                "赵获、赵成"
            ],
            [
                "时代",
                "春秋时期"
            ],
            [
                "名",
                "武"
            ],
            [
                "氏",
                "赵"
            ],
            [
                "姓",
                "嬴"
            ],
            [
                "父",
                "赵朔"
            ],
            [
                "谥号",
                "文"
            ],
            [
                "身份",
                "晋国新军佐 晋国新军将 晋国上军将 晋国中军佐 晋国中军将"
            ]
        ]
    },
    {
        "name": "巫臣",
        "infobox": [
            [
                "子女",
                "屈狐庸、叔向之妻"
            ],
            [
                "时代",
                "周朝"
            ],
            [
                "官位",
                "楚国申公、晋国邢大夫"
            ],
            [
                "名",
                "巫臣"
            ],
            [
                "氏",
                "屈"
            ],
            [
                "别称",
                "屈巫"
            ]
        ]
    },
    {
        "name": "夫差",
        "infobox": [
            [
                "在世",
                "不详─前473年"
            ],
            [
                "父",
                "阖闾"
            ],
            [
                "母",
                "不详"
            ],
            [
                "陵墓",
                "不详"
            ],
            [
                "在位",
                "前495年─前473年"
            ],
            [
                "政权",
                "吴国"
            ]
        ]
    },
    {
        "name": "伍尚",
        "infobox": [
            [
                "国家",
                "楚国"
            ],
            [
                "官位",
                "楚国大夫"
            ],
            [
                "逝世日期",
                "前522年"
            ],
            [
                "名",
                "尚"
            ],
            [
                "氏",
                "伍氏"
            ],
            [
                "别称",
                "棠君尚"
            ],
            [
                "父",
                "伍奢"
            ],
            [
                "出生日期",
                "约前550年"
            ]
        ]
    },
    {
        "name": "崔杼",
        "infobox": [
            [
                "子女",
                "崔成 崔彊 崔明"
            ],
            [
                "国家",
                "齐国"
            ],
            [
                "逝世日期",
                "前546年"
            ],
            [
                "名",
                "杼"
            ],
            [
                "氏",
                "崔"
            ],
            [
                "正妻",
                "东郭姜"
            ],
            [
                "姓",
                "姜"
            ],
            [
                "时代",
                "春秋"
            ],
            [
                "别名",
                "崔子、崔武子"
            ],
            [
                "父",
                "崔夭"
            ],
            [
                "谥号",
                "武"
            ],
            [
                "身份",
                "齐国右相"
            ]
        ]
    },
    {
        "name": "士会",
        "infobox": [
            [
                "子女",
                "士燮、士鲂"
            ],
            [
                "时代",
                "春秋时期"
            ],
            [
                "名",
                "会"
            ],
            [
                "氏",
                "士、范"
            ],
            [
                "姓",
                "祁"
            ],
            [
                "父",
                "成伯缺"
            ],
            [
                "谥号",
                "武"
            ],
            [
                "身份",
                "晋国代理车右 晋国上军将 晋国中军佐 晋国中军将、太傅"
            ]
        ]
    },
    {
        "name": "先轸",
        "infobox": [
            [
                "子女",
                "先且居"
            ],
            [
                "国家",
                "晋国"
            ],
            [
                "官位",
                "晋国中军将"
            ],
            [
                "名",
                "轸"
            ],
            [
                "氏",
                "先"
            ],
            [
                "姓",
                "祁"
            ],
            [
                "时代",
                "春秋"
            ],
            [
                "别名",
                "原轸"
            ],
            [
                "身份",
                "卿"
            ]
        ]
    },
    {
        "name": "孟献子",
        "infobox": [
            [
                "子女",
                "孟庄子仲孙速、仲孙它、懿伯"
            ],
            [
                "国家",
                "鲁国"
            ],
            [
                "逝世日期",
                "前554年"
            ],
            [
                "名",
                "蔑"
            ],
            [
                "别名",
                "仲孙蔑、孟献子"
            ],
            [
                "姓",
                "姬"
            ],
            [
                "时代",
                "春秋"
            ],
            [
                "氏",
                "孟孙"
            ],
            [
                "父",
                "孟文伯仲孙谷"
            ],
            [
                "出生日期",
                "约前624年"
            ],
            [
                "谥号",
                "献"
            ],
            [
                "身份",
                "鲁国卿"
            ]
        ]
    },
    {
        "name": "荀偃",
        "infobox": [
            [
                "子女",
                "荀吴"
            ],
            [
                "时代",
                "春秋时期"
            ],
            [
                "名",
                "偃"
            ],
            [
                "氏",
                "荀、中行"
            ],
            [
                "字",
                "伯游"
            ],
            [
                "父",
                "荀庚"
            ],
            [
                "谥号",
                "献"
            ]
        ]
    },
    {
        "name": "韩宣子",
        "infobox": [
            [
                "子女",
                "韩须"
            ],
            [
                "国家",
                "晋国"
            ],
            [
                "官位",
                "晋国中军将"
            ],
            [
                "名",
                "起"
            ],
            [
                "别名",
                "韩宣子"
            ],
            [
                "姓",
                "姬"
            ],
            [
                "时代",
                "春秋"
            ],
            [
                "氏",
                "韩"
            ],
            [
                "父",
                "韩厥"
            ],
            [
                "谥号",
                "宣"
            ],
            [
                "身份",
                "卿"
            ]
        ]
    },
    {
        "name": "赵盾",
        "infobox": [
            [
                "子女",
                "赵朔"
            ],
            [
                "国家",
                "晋国"
            ],
            [
                "官位",
                "晋国中军将"
            ],
            [
                "逝世日期",
                "公元前601年"
            ],
            [
                "名",
                "盾"
            ],
            [
                "母",
                "叔隗"
            ],
            [
                "氏",
                "赵"
            ],
            [
                "姓",
                "嬴"
            ],
            [
                "时代",
                "春秋时期"
            ],
            [
                "父",
                "赵衰"
            ],
            [
                "谥号",
                "宣"
            ],
            [
                "身份",
                "晋国赵氏家主"
            ]
        ]
    },
    {
        "name": "荀罃",
        "infobox": [
            [
                "子女",
                "荀朔（又名知朔）"
            ],
            [
                "国家",
                "晋国"
            ],
            [
                "官位",
                "晋国下军佐（公元前578年五月） 晋国上军佐（公元前574年） 晋国次卿、中军佐（公元前573年） 晋国正卿、中军将（公元前566年）"
            ],
            [
                "逝世日期",
                "公元前560年"
            ],
            [
                "名",
                "罃"
            ],
            [
                "氏",
                "荀氏、知氏（或智氏）"
            ],
            [
                "时代",
                "春秋时代"
            ],
            [
                "字",
                "子羽"
            ],
            [
                "父",
                "荀首"
            ],
            [
                "出生日期",
                "不明"
            ],
            [
                "谥号",
                "武"
            ]
        ]
    },
    {
        "name": "晏弱",
        "infobox": [
            [
                "国家",
                "齐国"
            ],
            [
                "官位",
                "齐国大夫"
            ],
            [
                "逝世日期",
                "前556年"
            ],
            [
                "名",
                "弱"
            ],
            [
                "太子",
                "晏婴"
            ],
            [
                "氏",
                "晏氏"
            ],
            [
                "别称",
                "晏桓子"
            ],
            [
                "出生地点",
                "莱之夷维"
            ],
            [
                "出生日期",
                "前635年"
            ],
            [
                "谥号",
                "桓"
            ]
        ]
    },
    {
        "name": "赵简子",
        "infobox": [
            [
                "子女",
                "赵伯鲁、赵襄子"
            ],
            [
                "国家",
                "晋国"
            ],
            [
                "官位",
                "晋国上军将 晋国正卿"
            ],
            [
                "逝世日期",
                "公元前476年"
            ],
            [
                "名",
                "鞅"
            ],
            [
                "氏",
                "赵氏"
            ],
            [
                "姓",
                "嬴"
            ],
            [
                "时代",
                "春秋时期"
            ],
            [
                "父",
                "赵成（赵景叔）"
            ],
            [
                "谥号",
                "简"
            ],
            [
                "身份",
                "晋国赵氏家主"
            ]
        ]
    },
    {
        "name": "羊舌赤",
        "infobox": [
            [
                "子女",
                "子容"
            ],
            [
                "时代",
                "春秋时期"
            ],
            [
                "名",
                "赤"
            ],
            [
                "氏",
                "羊舌"
            ],
            [
                "姓",
                "姬"
            ],
            [
                "字",
                "伯华"
            ],
            [
                "父",
                "羊舌职"
            ],
            [
                "身份",
                "晋国中军尉佐"
            ]
        ]
    },
    {
        "name": "羊舌职",
        "infobox": [
            [
                "子女",
                "伯华、叔向、叔鱼、叔虎、季夙"
            ],
            [
                "时代",
                "春秋时期"
            ],
            [
                "名",
                "职"
            ],
            [
                "氏",
                "羊舌"
            ],
            [
                "正妻",
                "羊舌姬"
            ],
            [
                "姓",
                "姬"
            ],
            [
                "父",
                "羊舌大夫"
            ],
            [
                "身份",
                "晋国中军尉佐"
            ]
        ]
    },
    {
        "name": "杨食我",
        "infobox": [
            [
                "姓",
                "姬"
            ],
            [
                "时代",
                "春秋时期"
            ],
            [
                "身份",
                "晋国大夫"
            ],
            [
                "氏",
                "羊舌氏、杨氏"
            ],
            [
                "父",
                "杨誉"
            ]
        ]
    },
    {
        "name": "臧文仲",
        "infobox": [
            [
                "子女",
                "臧宣叔臧孙许"
            ],
            [
                "国家",
                "鲁国"
            ],
            [
                "名",
                "辰"
            ],
            [
                "氏",
                "臧孙"
            ],
            [
                "姓",
                "姬"
            ],
            [
                "时代",
                "春秋"
            ],
            [
                "别名",
                "臧文仲"
            ],
            [
                "父",
                "伯氏瓶"
            ],
            [
                "谥号",
                "宣"
            ],
            [
                "身份",
                "鲁国大夫"
            ]
        ]
    },
    {
        "name": "臧武仲",
        "infobox": [
            [
                "国家",
                "鲁国"
            ],
            [
                "名",
                "纥"
            ],
            [
                "氏",
                "臧孙"
            ],
            [
                "姓",
                "姬"
            ],
            [
                "时代",
                "东周春秋时期"
            ],
            [
                "别名",
                "臧武仲、臧孙纥"
            ],
            [
                "父",
                "臧宣叔臧孙许"
            ],
            [
                "身份",
                "鲁国大夫"
            ]
        ]
    },
    {
        "name": "臧宣叔",
        "infobox": [
            [
                "子女",
                "臧贾、臧纥、臧为、臧畴"
            ],
            [
                "国家",
                "鲁国"
            ],
            [
                "名",
                "许"
            ],
            [
                "氏",
                "臧孙"
            ],
            [
                "姓",
                "姬"
            ],
            [
                "时代",
                "春秋"
            ],
            [
                "别名",
                "臧宣叔"
            ],
            [
                "父",
                "臧文仲臧孙辰"
            ],
            [
                "谥号",
                "宣"
            ],
            [
                "身份",
                "鲁国大夫"
            ]
        ]
    },
    {
        "name": "赵括",
        "infobox": [
            [
                "国家",
                "赵国"
            ],
            [
                "官位",
                "赵国大将"
            ],
            [
                "逝世日期",
                "公元前260年"
            ],
            [
                "名",
                "括"
            ],
            [
                "氏",
                "赵氏"
            ],
            [
                "时代",
                "战国时期"
            ],
            [
                "父",
                "马服君赵奢"
            ],
            [
                "出生日期",
                "约公元前310年"
            ],
            [
                "身份",
                "马服君赵奢之子"
            ]
        ]
    },
    {
        "name": "赵同",
        "infobox": [
            [
                "国家",
                "晋国"
            ],
            [
                "官位",
                "晋国下军大夫 晋国下军佐"
            ],
            [
                "逝世日期",
                "前583年"
            ],
            [
                "名",
                "同"
            ],
            [
                "氏",
                "赵"
            ],
            [
                "姓",
                "嬴"
            ],
            [
                "别称",
                "原同、原叔"
            ]
        ]
    },
    {
        "name": "郑庄公",
        "infobox": [
            [
                "政权",
                "郑国"
            ],
            [
                "谥号",
                "庄公"
            ],
            [
                "在世",
                "前757年—前701年"
            ],
            [
                "陵墓",
                "不明"
            ],
            [
                "在位",
                "前744年—前701年"
            ]
        ]
    },
    {
        "name": "鲁庄公",
        "infobox": [
            [
                "年号",
                "无"
            ],
            [
                "在世",
                "前706年10月7日－前662年8月11日（阴历八月初五癸亥）"
            ],
            [
                "父",
                "鲁桓公"
            ],
            [
                "母",
                "文姜"
            ],
            [
                "陵墓",
                "不详"
            ],
            [
                "在位",
                "前693年正月－前662年8月11日"
            ],
            [
                "谥号",
                "庄公"
            ],
            [
                "政权",
                "鲁国"
            ]
        ]
    },
    {
        "name": "子产",
        "infobox": [
            [
                "子女",
                "国参"
            ],
            [
                "时代",
                "春秋时期"
            ],
            [
                "名",
                "侨"
            ],
            [
                "氏",
                "国"
            ],
            [
                "姓",
                "姬"
            ],
            [
                "别字",
                "字美"
            ],
            [
                "字",
                "子产"
            ],
            [
                "父",
                "子国"
            ],
            [
                "谥号",
                "成"
            ],
            [
                "身份",
                "郑国为政"
            ]
        ]
    },
    {
        "name": "子荡",
        "infobox": [
            [
                "时代",
                "春秋时期"
            ],
            [
                "名",
                "罢"
            ],
            [
                "氏",
                "薳"
            ],
            [
                "姓",
                "芈"
            ],
            [
                "字",
                "子荡"
            ],
            [
                "身份",
                "楚国令尹"
            ]
        ]
    },
    {
        "name": "子服惠伯",
        "infobox": [
            [
                "子女",
                "子服昭伯"
            ],
            [
                "国家",
                "鲁"
            ],
            [
                "名",
                "椒"
            ],
            [
                "氏",
                "子服"
            ],
            [
                "姓",
                "姬"
            ],
            [
                "时代",
                "春秋"
            ],
            [
                "别名",
                "湫"
            ],
            [
                "父",
                "仲孙它"
            ],
            [
                "谥号",
                "惠"
            ]
        ]
    },
    {
        "name": "子服景伯",
        "infobox": [
            [
                "国家",
                "鲁"
            ],
            [
                "名",
                "何"
            ],
            [
                "氏",
                "子服"
            ],
            [
                "姓",
                "姬"
            ],
            [
                "时代",
                "春秋"
            ],
            [
                "父",
                "子服昭伯"
            ],
            [
                "谥号",
                "景"
            ]
        ]
    },
    {
        "name": "子服昭伯",
        "infobox": [
            [
                "子女",
                "子服景伯"
            ],
            [
                "国家",
                "鲁"
            ],
            [
                "名",
                "回"
            ],
            [
                "氏",
                "子服"
            ],
            [
                "姓",
                "姬"
            ],
            [
                "时代",
                "春秋"
            ],
            [
                "父",
                "子服惠伯"
            ],
            [
                "谥号",
                "昭"
            ]
        ]
    },
    {
        "name": "子皮",
        "infobox": [
            [
                "子女",
                "罕婴齐"
            ],
            [
                "国家",
                "郑"
            ],
            [
                "名",
                "虎"
            ],
            [
                "氏",
                "罕"
            ],
            [
                "姓",
                "姬"
            ],
            [
                "时代",
                "春秋"
            ],
            [
                "字",
                "子皮"
            ],
            [
                "父",
                "子展"
            ],
            [
                "身份",
                "郑国当国"
            ]
        ]
    },
    {
        "name": "子野",
        "infobox": [
            [
                "国家",
                "鲁国"
            ],
            [
                "在位年代",
                "前542年六月－九月"
            ],
            [
                "逝世日期",
                "前542年"
            ],
            [
                "名",
                "野"
            ],
            [
                "姓",
                "姬"
            ],
            [
                "父",
                "鲁襄公"
            ]
        ]
    },
    {
        "name": "子展",
        "infobox": [
            [
                "子女",
                "罕虎、罕魋"
            ],
            [
                "国家",
                "郑"
            ],
            [
                "名",
                "舍之"
            ],
            [
                "氏",
                "罕"
            ],
            [
                "姓",
                "姬"
            ],
            [
                "时代",
                "春秋"
            ],
            [
                "字",
                "子展"
            ],
            [
                "父",
                "子罕"
            ],
            [
                "身份",
                "郑国当国"
            ]
        ]
    },
    {
        "name": "沈尹戌",
        "infobox": [
            [
                "子女",
                "叶公高"
            ],
            [
                "国家",
                "楚国"
            ],
            [
                "名",
                "戌"
            ],
            [
                "氏",
                "沈尹"
            ],
            [
                "姓",
                "芈"
            ],
            [
                "时代",
                "春秋时期"
            ],
            [
                "身份",
                "左司马"
            ]
        ]
    }
]